einsumt.py
einsumt-0.9.4.dist-info/LICENSE
einsumt-0.9.4.dist-info/METADATA
einsumt-0.9.4.dist-info/WHEEL
einsumt-0.9.4.dist-info/top_level.txt
einsumt-0.9.4.dist-info/RECORD
