Metadata-Version: 2.1
Name: einsumt
Version: 0.9.4
Summary: Multithreaded version of numpy.einsum function
Home-page: https://github.com/mrkwjc/einsumt
Author: Marek Wojciechowski
Author-email: mrkwjc@gmail.com
License: MIT
Keywords: numpy,einsum,hpc
Classifier: Programming Language :: Python :: 2
Classifier: Programming Language :: Python :: 3
Classifier: License :: OSI Approved :: MIT License
Classifier: Operating System :: OS Independent
Requires-Python: >=2.7
License-File: LICENSE
